vickers_hardness/__init__.py
vickers_hardness/generate_des.py
vickers_hardness/hv_cv.py
vickers_hardness/hv_prediction.py
vickers_hardness/vickers_hardness_.py
vickers_hardness/data/__init__.py
vickers_hardness/data/elementsnew.csv
vickers_hardness/data/elementsnew.xlsx
vickers_hardness/data/hv_comp_load.csv
vickers_hardness/data/hv_comp_load.xlsx
vickers_hardness/data/hv_des.csv
vickers_hardness/data/hv_des.xlsx
vickers_hardness/examples/mpds.py
vickers_hardness/examples/mpds_dataset_compare.py
vickers_hardness/tests/test_vickers_hardness.py
vickers_hardness/utils/__init__.py
vickers_hardness/utils/plotting.py
vickers_hardness/utils/uncertainty.py
vickers_hardness-0.1.9.dist-info/LICENSE
vickers_hardness-0.1.9.dist-info/WHEEL
vickers_hardness-0.1.9.dist-info/METADATA
vickers_hardness-0.1.9.dist-info/RECORD
