Metadata-Version: 2.1
Name: vickers_hardness
Version: 0.1.9
Summary: Predicting load dependent Vickers hardness based on chemical composition.
Author: Ziyan Zhang
Author-email: "Sterling G. Baird" <sterling.baird@utah.edu>
Classifier: License :: OSI Approved :: MIT License
Classifier: Operating System :: OS Independent
Requires-Dist: plotly
Requires-Dist: kaleido
Requires-Dist: pandas
Requires-Dist: pymatgen
Requires-Dist: matplotlib
Requires-Dist: numpy
Requires-Dist: scikit_learn
Requires-Dist: xgboost
Requires-Dist: shap_hypetune
Project-URL: Home, https://github.com/sparks-baird/vickers_hardness
